acapy_client/__init__.py
acapy_client/api/__init__.py
acapy_client/api/action_menu/__init__.py
acapy_client/api/action_menu/post_action_menu_conn_id_close.py
acapy_client/api/action_menu/post_action_menu_conn_id_fetch.py
acapy_client/api/action_menu/post_action_menu_conn_id_perform.py
acapy_client/api/action_menu/post_action_menu_conn_id_request.py
acapy_client/api/action_menu/post_action_menu_conn_id_send_menu.py
acapy_client/api/basicmessage/__init__.py
acapy_client/api/basicmessage/send_basicmessage.py
acapy_client/api/connection/__init__.py
acapy_client/api/connection/create_invitation.py
acapy_client/api/connection/create_static.py
acapy_client/api/connection/delete_connection.py
acapy_client/api/connection/get_connection.py
acapy_client/api/connection/get_connections.py
acapy_client/api/connection/get_connections_conn_id_endpoints.py
acapy_client/api/connection/get_metadata.py
acapy_client/api/connection/post_connections_conn_id_accept_invitation.py
acapy_client/api/connection/post_connections_conn_id_accept_request.py
acapy_client/api/connection/post_connections_conn_id_establish_inbound_ref_id.py
acapy_client/api/connection/receive_invitation.py
acapy_client/api/connection/set_metadata.py
acapy_client/api/credential_definition/__init__.py
acapy_client/api/credential_definition/get_credential_definitions_created.py
acapy_client/api/credential_definition/get_credential_definitions_cred_def_id.py
acapy_client/api/credential_definition/post_credential_definitions_cred_def_id_write_record.py
acapy_client/api/credential_definition/publish_cred_def.py
acapy_client/api/credentials/__init__.py
acapy_client/api/credentials/delete_credential_credential_id.py
acapy_client/api/credentials/delete_w3c_credential.py
acapy_client/api/credentials/get_credential_credential_id.py
acapy_client/api/credentials/get_credential_mime_types_credential_id.py
acapy_client/api/credentials/get_credential_revoked_credential_id.py
acapy_client/api/credentials/get_credentials.py
acapy_client-0.7.4.dist-info/LICENSE
acapy_client-0.7.4.dist-info/WHEEL
acapy_client-0.7.4.dist-info/METADATA
acapy_client-0.7.4.dist-info/RECORD
