Metadata-Version: 2.1
Name: acapy-client
Version: 0.7.4
Summary: A client library for accessing Aries Cloud Agent
Requires-Python: >=3.7,<4.0
Classifier: Programming Language :: Python :: 3
Classifier: Programming Language :: Python :: 3.10
Classifier: Programming Language :: Python :: 3.7
Classifier: Programming Language :: Python :: 3.8
Classifier: Programming Language :: Python :: 3.9
Requires-Dist: attrs (>=21.3.0)
Requires-Dist: httpx (>=0.15.4,<0.23.0)
Requires-Dist: python-dateutil (>=2.8.0,<3.0.0)
